Techv_ai/__init__.py
Techv_ai/chat.py
Techv_ai/client.py
techvllm_ai-0.1.0.dist-info/LICENCE
techvllm_ai-0.1.0.dist-info/METADATA
techvllm_ai-0.1.0.dist-info/WHEEL
techvllm_ai-0.1.0.dist-info/top_level.txt
techvllm_ai-0.1.0.dist-info/RECORD
